questfoundry_compiler/README.md
questfoundry_compiler/__init__.py
questfoundry_compiler/assemblers.py
questfoundry_compiler/build_hooks.py
questfoundry_compiler/cli.py
questfoundry_compiler/manifest_builder.py
questfoundry_compiler/py.typed
questfoundry_compiler/spec_compiler.py
questfoundry_compiler/spec_fetcher.py
questfoundry_compiler/types.py
questfoundry_compiler/validators.py
questfoundry_compiler/_bundled_spec/01-roles/charters/all.md
questfoundry_compiler/_bundled_spec/01-roles/charters/art_director.md
questfoundry_compiler/_bundled_spec/01-roles/charters/audio_director.md
questfoundry_compiler/_bundled_spec/01-roles/charters/audio_producer.md
questfoundry_compiler/_bundled_spec/01-roles/charters/book_binder.md
questfoundry_compiler/_bundled_spec/01-roles/charters/codex_curator.md
questfoundry_compiler/_bundled_spec/01-roles/charters/gatekeeper.md
questfoundry_compiler/_bundled_spec/01-roles/charters/illustrator.md
questfoundry_compiler/_bundled_spec/01-roles/charters/lore_weaver.md
questfoundry_compiler/_bundled_spec/01-roles/charters/player_narrator.md
questfoundry_compiler/_bundled_spec/01-roles/charters/plotwright.md
questfoundry_compiler/_bundled_spec/01-roles/charters/researcher.md
questfoundry_compiler/_bundled_spec/01-roles/charters/scene_smith.md
questfoundry_compiler/_bundled_spec/01-roles/charters/showrunner.md
questfoundry_compiler/_bundled_spec/01-roles/charters/style_lead.md
questfoundry_compiler/_bundled_spec/01-roles/charters/translator.md
questfoundry_compiler/_bundled_spec/03-schemas/README.md
questfoundry_compiler/_bundled_spec/03-schemas/SCHEMA_INDEX.json
questfoundry_compiler/_bundled_spec/03-schemas/action_items.schema.json
questfoundry_compiler/_bundled_spec/03-schemas/anchor_map.schema.json
questfoundry_compiler/_bundled_spec/03-schemas/archive_manifest.schema.json
questfoundry_compiler/_bundled_spec/03-schemas/art_manifest.schema.json
questfoundry_compiler/_bundled_spec/03-schemas/art_plan.schema.json
questfoundry_compiler-0.6.0.dist-info/METADATA
questfoundry_compiler-0.6.0.dist-info/WHEEL
questfoundry_compiler-0.6.0.dist-info/entry_points.txt
questfoundry_compiler-0.6.0.dist-info/licenses/LICENSE
questfoundry_compiler-0.6.0.dist-info/RECORD
