Metadata-Version: 2.4
Name: questfoundry-compiler
Version: 0.6.0
Summary: Spec compiler for QuestFoundry - transforms atomic behavior primitives into runtime artifacts
Project-URL: Homepage, https://github.com/pvliesdonk/questfoundry
Project-URL: Documentation, https://github.com/pvliesdonk/questfoundry-spec
Project-URL: Repository, https://github.com/pvliesdonk/questfoundry
Project-URL: Bug Tracker, https://github.com/pvliesdonk/questfoundry/issues
Author-email: Peter Liesdonk <peter@liesdonk.nl>
License: MIT
License-File: LICENSE
Keywords: behavior-primitives,compiler,interactive-fiction,questfoundry,spec-compiler
Classifier: Development Status :: 3 - Alpha
Classifier: Intended Audience :: Developers
Classifier: License :: OSI Approved :: MIT License
Classifier: Programming Language :: Python :: 3
Classifier: Programming Language :: Python :: 3.11
Classifier: Programming Language :: Python :: 3.12
Classifier: Programming Language :: Python :: 3.13
Classifier: Programming Language :: Python :: 3.14
Classifier: Topic :: Software Development :: Code Generators
Classifier: Topic :: Software Development :: Compilers
Classifier: Typing :: Typed
Requires-Python: >=3.11
Requires-Dist: click>=8.0.0
Requires-Dist: pyyaml>=6.0
Requires-Dist: questionary>=2.0.0
Requires-Dist: rich>=13.0.0
Requires-Dist: typer>=0.9.0
Provides-Extra: dev
Requires-Dist: commitizen>=3.12.0; extra == 'dev'
Requires-Dist: mypy>=1.0; extra == 'dev'
Requires-Dist: pre-commit>=3.0; extra == 'dev'
Requires-Dist: pytest-cov>=4.0; extra == 'dev'
Requires-Dist: pytest>=7.0; extra == 'dev'
Requires-Dist: ruff>=0.1.0; extra == 'dev'
Requires-Dist: types-pyyaml>=6.0; extra == 'dev'
